wheel_axle/bdist_axle/__init__.py
wheel_axle/bdist_axle/_file_utils.py
wheel_axle-0.0.11.dist-info/METADATA
wheel_axle-0.0.11.dist-info/WHEEL
wheel_axle-0.0.11.dist-info/entry_points.txt
wheel_axle-0.0.11.dist-info/namespace_packages.txt
wheel_axle-0.0.11.dist-info/top_level.txt
wheel_axle-0.0.11.dist-info/zip-safe
wheel_axle-0.0.11.dist-info/RECORD
