Metadata-Version: 2.4
Name: wheel_axle
Version: 0.0.11
Summary: Axle is Python wheel enhancement library
Home-page: https://github.com/karellen/wheel-axle
Author: Karellen, Inc.
Author-email: supervisor@karellen.co
Maintainer: Arcadiy Ivanov
Maintainer-email: arcadiy@karellen.co
License: Apache License, Version 2.0
Project-URL: Bug Tracker, https://github.com/karellen/wheel-axle/issues
Project-URL: Documentation, https://github.com/karellen/wheel-axle/
Project-URL: Source Code, https://github.com/karellen/wheel-axle/
Keywords: wheel packaging setuptools bdist_wheel symlink postinstall
Classifier: License :: OSI Approved :: Apache Software License
Classifier: Programming Language :: Python :: 3.7
Classifier: Programming Language :: Python :: 3.8
Classifier: Programming Language :: Python :: 3.9
Classifier: Programming Language :: Python :: 3.10
Classifier: Programming Language :: Python :: 3.11
Classifier: Programming Language :: Python :: 3.12
Classifier: Programming Language :: Python :: 3.13
Classifier: Operating System :: MacOS :: MacOS X
Classifier: Operating System :: POSIX
Classifier: Operating System :: POSIX :: Linux
Classifier: Topic :: System :: Archiving :: Packaging
Classifier: Topic :: Software Development :: Build Tools
Classifier: Intended Audience :: Developers
Classifier: Development Status :: 4 - Beta
Requires-Python: >=3.9
Requires-Dist: wheel>=0.37.0
Requires-Dist: wheel-axle-runtime<1.0,>0.0.5
Dynamic: author
Dynamic: author-email
Dynamic: classifier
Dynamic: description
Dynamic: description-content-type
Dynamic: home-page
Dynamic: keywords
Dynamic: license
Dynamic: maintainer
Dynamic: maintainer-email
Dynamic: project-url
Dynamic: requires-dist
Dynamic: requires-python
Dynamic: summary
